{"@type":"Software","id":"http://imcr.ontosoft.org/repository/software/Software-rG7gI1IEg837","name":"Software-rG7gI1IEg837","type":"http://ontosoft.org/software#Software","label":"drunken-data-quality","value":{"http://ontosoft.org/software#hasActiveDevelopment":[{"@type":"TextEntity","id":"http://imcr.ontosoft.org/repository/software/Software-rG7gI1IEg837#DevelopmentInformation-bCLqWySfxvUj","name":"DevelopmentInformation-bCLqWySfxvUj","type":"http://ontosoft.org/software#DevelopmentInformation","value":"https://github.com/FRosner/drunken-data-quality"}],"http://ontosoft.org/software#hasAdopter":[],"http://ontosoft.org/software#hasAverageRunTime":[],"http://ontosoft.org/software#hasBenchmarkInformation":[],"http://ontosoft.org/software#hasCodeLocation":[{"@type":"Location","id":"http://imcr.ontosoft.org/repository/software/Software-rG7gI1IEg837#Location-cPCYeMG1hIKl","name":"Location-cPCYeMG1hIKl","type":"http://ontosoft.org/software#Location","value":"https://github.com/FRosner/drunken-data-quality"}],"http://ontosoft.org/software#hasCommitmentOfSupport":[{"@type":"TextEntity","id":"http://imcr.ontosoft.org/repository/software/Software-rG7gI1IEg837#TextEntity-cdGWc1kBjQVv","name":"TextEntity-cdGWc1kBjQVv","type":"http://ontosoft.org/software#TextEntity","value":"https://github.com/FRosner/drunken-data-quality/issues"}],"http://ontosoft.org/software#hasCompositionDescription":[],"http://ontosoft.org/software#hasCreator":[{"@type":"EnumerationEntity","id":"http://imcr.ontosoft.org/repository/software/enumerations#Agent-npxJNoUhazDg","name":"Agent-npxJNoUhazDg","type":"http://www.w3.org/ns/prov#Agent","label":"Aleksander Sorokoumov","value":"Aleksander Sorokoumov"}],"http://ontosoft.org/software#hasDependency":[],"http://ontosoft.org/software#hasDocumentation":[{"@type":"Location","id":"http://imcr.ontosoft.org/repository/software/Software-rG7gI1IEg837#Location-XvDQcpBU7dqn","name":"Location-XvDQcpBU7dqn","type":"http://ontosoft.org/software#Location","value":"https://github.com/FRosner/drunken-data-quality"}],"http://ontosoft.org/software#hasDomainKeywords":[],"http://ontosoft.org/software#hasEmailContact":[],"http://ontosoft.org/software#hasExecutableLocation":[],"http://ontosoft.org/software#hasFundingSources":[],"http://ontosoft.org/software#hasImplementationLanguage":[{"@type":"EnumerationEntity","id":"http://ontosoft.org/software#Python","name":"Python","type":"http://ontosoft.org/software#ProgrammingLanguage","label":"Python","value":"Python"}],"http://ontosoft.org/software#hasInput":[],"http://ontosoft.org/software#hasInputParameter":[],"http://ontosoft.org/software#hasInstallationInstructions":[],"http://ontosoft.org/software#hasInteroperableSoftware":[],"http://ontosoft.org/software#hasLicense":[{"@type":"EnumerationEntity","id":"http://ontosoft.org/software#ALv2","name":"ALv2","type":"http://ontosoft.org/software#License","label":"Apache License 2.0","value":"Apache License 2.0"}],"http://ontosoft.org/software#hasMajorContributor":[],"http://ontosoft.org/software#hasName":[{"@type":"TextEntity","id":"http://imcr.ontosoft.org/repository/software/Software-rG7gI1IEg837#TextEntity-Qw7EAyljDfWu","name":"TextEntity-Qw7EAyljDfWu","type":"http://ontosoft.org/software#TextEntity","value":"drunken-data-quality"}],"http://ontosoft.org/software#hasOtherImplementationDetails":[],"http://ontosoft.org/software#hasOutput":[],"http://ontosoft.org/software#hasPreferredCitation":[],"http://ontosoft.org/software#hasProjectWebsite":[{"@type":"Location","id":"http://imcr.ontosoft.org/repository/software/Software-rG7gI1IEg837#Location-8jSZm2q5v6YH","name":"Location-8jSZm2q5v6YH","type":"http://ontosoft.org/software#Location","value":"https://github.com/FRosner/drunken-data-quality"}],"http://ontosoft.org/software#hasPublisher":[],"http://ontosoft.org/software#hasRating":[],"http://ontosoft.org/software#hasRelevantDataSources":[],"http://ontosoft.org/software#hasSalientQualities":[],"http://ontosoft.org/software#hasShortDescription":[{"@type":"TextEntity","id":"http://imcr.ontosoft.org/repository/software/Software-rG7gI1IEg837#TextEntity-KyN2zf9PtrCQ","name":"TextEntity-KyN2zf9PtrCQ","type":"http://ontosoft.org/software#TextEntity","value":"DDQ is a small library for checking constraints on Spark data structures. It can be used to assure a certain data quality, especially when continuous imports happen."}],"http://ontosoft.org/software#hasSoftwareCategory":[{"@type":"EnumerationEntity","id":"http://imcr.ontosoft.org/repository/software/enumerations#SoftwareCategory-gtib5Wlg3FGZ","name":"SoftwareCategory-gtib5Wlg3FGZ","type":"http://ontosoft.org/software#SoftwareCategory","label":"quality control","value":"quality control"},{"@type":"EnumerationEntity","id":"http://imcr.ontosoft.org/repository/software/enumerations#SoftwareCategory-bR7VLgRGWmaC","name":"SoftwareCategory-bR7VLgRGWmaC","type":"http://ontosoft.org/software#SoftwareCategory","label":"assurance","value":"assurance"}],"http://ontosoft.org/software#hasSoftwareCommunity":[],"http://ontosoft.org/software#hasSoftwareSupport":[],"http://ontosoft.org/software#hasSoftwareVersion":[],"http://ontosoft.org/software#hasTestData":[],"http://ontosoft.org/software#hasTestInstructions":[],"http://ontosoft.org/software#hasUniqueId":[],"http://ontosoft.org/software#hasUsageInformation":[],"http://ontosoft.org/software#hasUseLimitations":[],"http://ontosoft.org/software#hasUseStatistics":[],"http://ontosoft.org/software#hasUsesAndAssumptions":[],"http://ontosoft.org/software#requiresAverageMemory":[],"http://ontosoft.org/software#similarSoftware":[],"http://ontosoft.org/software#supportsOperatingSystem":[],"http://ontosoft.org/software#usedInPublication":[]},"provenance":{"id":"http://imcr.ontosoft.org/repository/software/Software-rG7gI1IEg837/provenance","entities":{"http://imcr.ontosoft.org/repository/software/enumerations#SoftwareCategory-80enJQY5r09D":{"id":"http://imcr.ontosoft.org/repository/software/enumerations#SoftwareCategory-80enJQY5r09D","revisionOf":{},"generatedBy":"http://imcr.ontosoft.org/repository/software/Software-rG7gI1IEg837/provenance#Update-BS5Bq1fLBXi2","invalidatedBy":"http://imcr.ontosoft.org/repository/software/Software-rG7gI1IEg837/provenance#Update-5vTWBNnsXbSc"},"http://imcr.ontosoft.org/repository/software/Software-rG7gI1IEg837#TextEntity-Qw7EAyljDfWu":{"id":"http://imcr.ontosoft.org/repository/software/Software-rG7gI1IEg837#TextEntity-Qw7EAyljDfWu","revisionOf":{},"generatedBy":"http://imcr.ontosoft.org/repository/software/Software-rG7gI1IEg837/provenance#Update-BS5Bq1fLBXi2","invalidatedBy":{}},"http://imcr.ontosoft.org/repository/software/Software-rG7gI1IEg837#Location-cPCYeMG1hIKl":{"id":"http://imcr.ontosoft.org/repository/software/Software-rG7gI1IEg837#Location-cPCYeMG1hIKl","revisionOf":{},"generatedBy":"http://imcr.ontosoft.org/repository/software/Software-rG7gI1IEg837/provenance#Update-BS5Bq1fLBXi2","invalidatedBy":{}},"http://imcr.ontosoft.org/repository/software/Software-rG7gI1IEg837":{"id":"http://imcr.ontosoft.org/repository/software/Software-rG7gI1IEg837","revisionOf":{},"generatedBy":"http://imcr.ontosoft.org/repository/software/Software-rG7gI1IEg837/provenance#Create-RTjqhkWL36qA","invalidatedBy":{}},"http://imcr.ontosoft.org/repository/software/Software-rG7gI1IEg837#Location-XvDQcpBU7dqn":{"id":"http://imcr.ontosoft.org/repository/software/Software-rG7gI1IEg837#Location-XvDQcpBU7dqn","revisionOf":{},"generatedBy":"http://imcr.ontosoft.org/repository/software/Software-rG7gI1IEg837/provenance#Update-BS5Bq1fLBXi2","invalidatedBy":{}},"http://ontosoft.org/software#Python":{"id":"http://ontosoft.org/software#Python","revisionOf":{},"generatedBy":"http://imcr.ontosoft.org/repository/software/Software-rG7gI1IEg837/provenance#Update-ugqoi1JjHwzc","invalidatedBy":{}},"http://ontosoft.org/software#ALv2":{"id":"http://ontosoft.org/software#ALv2","revisionOf":{},"generatedBy":"http://imcr.ontosoft.org/repository/software/Software-rG7gI1IEg837/provenance#Update-BS5Bq1fLBXi2","invalidatedBy":{}},"http://imcr.ontosoft.org/repository/software/Software-rG7gI1IEg837#Location-8jSZm2q5v6YH":{"id":"http://imcr.ontosoft.org/repository/software/Software-rG7gI1IEg837#Location-8jSZm2q5v6YH","revisionOf":{},"generatedBy":"http://imcr.ontosoft.org/repository/software/Software-rG7gI1IEg837/provenance#Update-BS5Bq1fLBXi2","invalidatedBy":{}},"http://imcr.ontosoft.org/repository/software/enumerations#SoftwareCategory-bR7VLgRGWmaC":{"id":"http://imcr.ontosoft.org/repository/software/enumerations#SoftwareCategory-bR7VLgRGWmaC","revisionOf":{},"generatedBy":"http://imcr.ontosoft.org/repository/software/Software-rG7gI1IEg837/provenance#Update-BS5Bq1fLBXi2","invalidatedBy":{}},"http://imcr.ontosoft.org/repository/software/Software-rG7gI1IEg837#Agent-rtDaOwWTO1xK":{"id":"http://imcr.ontosoft.org/repository/software/Software-rG7gI1IEg837#Agent-rtDaOwWTO1xK","revisionOf":{},"generatedBy":"http://imcr.ontosoft.org/repository/software/Software-rG7gI1IEg837/provenance#Update-BS5Bq1fLBXi2","invalidatedBy":{}},"http://imcr.ontosoft.org/repository/software/Software-rG7gI1IEg837#DevelopmentInformation-bCLqWySfxvUj":{"id":"http://imcr.ontosoft.org/repository/software/Software-rG7gI1IEg837#DevelopmentInformation-bCLqWySfxvUj","revisionOf":{},"generatedBy":"http://imcr.ontosoft.org/repository/software/Software-rG7gI1IEg837/provenance#Update-BS5Bq1fLBXi2","invalidatedBy":{}},"http://imcr.ontosoft.org/repository/software/enumerations#ProgrammingLanguage-vNFafGW7oKdS":{"id":"http://imcr.ontosoft.org/repository/software/enumerations#ProgrammingLanguage-vNFafGW7oKdS","revisionOf":{},"generatedBy":{},"invalidatedBy":"http://imcr.ontosoft.org/repository/software/Software-rG7gI1IEg837/provenance#Update-ugqoi1JjHwzc"},"http://imcr.ontosoft.org/repository/software/Software-rG7gI1IEg837#TextEntity-cdGWc1kBjQVv":{"id":"http://imcr.ontosoft.org/repository/software/Software-rG7gI1IEg837#TextEntity-cdGWc1kBjQVv","revisionOf":{},"generatedBy":"http://imcr.ontosoft.org/repository/software/Software-rG7gI1IEg837/provenance#Update-BS5Bq1fLBXi2","invalidatedBy":{}},"http://imcr.ontosoft.org/repository/software/Software-rG7gI1IEg837#ProgrammingLanguage-uJLnh5cZc39a":{"id":"http://imcr.ontosoft.org/repository/software/Software-rG7gI1IEg837#ProgrammingLanguage-uJLnh5cZc39a","revisionOf":{},"generatedBy":"http://imcr.ontosoft.org/repository/software/Software-rG7gI1IEg837/provenance#Update-BS5Bq1fLBXi2","invalidatedBy":{}},"http://imcr.ontosoft.org/repository/software/Software-rG7gI1IEg837#TextEntity-KyN2zf9PtrCQ":{"id":"http://imcr.ontosoft.org/repository/software/Software-rG7gI1IEg837#TextEntity-KyN2zf9PtrCQ","revisionOf":{},"generatedBy":"http://imcr.ontosoft.org/repository/software/Software-rG7gI1IEg837/provenance#Update-BS5Bq1fLBXi2","invalidatedBy":{}},"http://imcr.ontosoft.org/repository/software/enumerations#SoftwareCategory-gtib5Wlg3FGZ":{"id":"http://imcr.ontosoft.org/repository/software/enumerations#SoftwareCategory-gtib5Wlg3FGZ","revisionOf":{},"generatedBy":"http://imcr.ontosoft.org/repository/software/Software-rG7gI1IEg837/provenance#Update-5vTWBNnsXbSc","invalidatedBy":{}}},"activities":{"http://imcr.ontosoft.org/repository/software/Software-rG7gI1IEg837/provenance#Update-BS5Bq1fLBXi2":{"id":"http://imcr.ontosoft.org/repository/software/Software-rG7gI1IEg837/provenance#Update-BS5Bq1fLBXi2","time":1562530966001,"agentId":"http://imcr.ontosoft.org/repository/users/csmith"},"http://imcr.ontosoft.org/repository/software/Software-rG7gI1IEg837/provenance#Update-ugqoi1JjHwzc":{"id":"http://imcr.ontosoft.org/repository/software/Software-rG7gI1IEg837/provenance#Update-ugqoi1JjHwzc","time":1562964427499,"agentId":"http://imcr.ontosoft.org/repository/users/admin"},"http://imcr.ontosoft.org/repository/software/Software-rG7gI1IEg837/provenance#Update-5vTWBNnsXbSc":{"id":"http://imcr.ontosoft.org/repository/software/Software-rG7gI1IEg837/provenance#Update-5vTWBNnsXbSc","time":1562902065860,"agentId":"http://imcr.ontosoft.org/repository/users/csmith"},"http://imcr.ontosoft.org/repository/software/Software-rG7gI1IEg837/provenance#Create-RTjqhkWL36qA":{"id":"http://imcr.ontosoft.org/repository/software/Software-rG7gI1IEg837/provenance#Create-RTjqhkWL36qA","time":1562530823481,"agentId":"http://imcr.ontosoft.org/repository/users/csmith"}},"agents":{"http://imcr.ontosoft.org/repository/users/csmith":{"id":"http://imcr.ontosoft.org/repository/users/csmith","name":"csmith"},"http://imcr.ontosoft.org/repository/users/admin":{"id":"http://imcr.ontosoft.org/repository/users/admin","name":"admin"}}},"permission":{"id":"http://imcr.ontosoft.org/repository/software/Software-rG7gI1IEg837/permission","owners":[{"id":"http://imcr.ontosoft.org/repository/users/csmith"}],"type":{},"authorizations":{"http://imcr.ontosoft.org/repository/software/Software-rG7gI1IEg837/permission#Auth-wYMqhFa0lzoB":{"id":"http://imcr.ontosoft.org/repository/software/Software-rG7gI1IEg837/permission#Auth-wYMqhFa0lzoB","agentId":"http://imcr.ontosoft.org/repository/users/csmith","agentName":"csmith","accessMode":{"id":"http://www.w3.org/ns/auth/acl#Write","mode":"Write"},"accessToObjId":"http://imcr.ontosoft.org/repository/software/Software-rG7gI1IEg837"}}}}
