{"@type":"Software","id":"http://imcr.ontosoft.org/repository/software/Software-rNPaVbUcYRkB","name":"Software-rNPaVbUcYRkB","type":"http://ontosoft.org/software#Software","label":"taxizedb","value":{"http://ontosoft.org/software#hasActiveDevelopment":[{"@type":"TextEntity","id":"http://imcr.ontosoft.org/repository/software/Software-rNPaVbUcYRkB#DevelopmentInformation-tzKaZHafsX2t","name":"DevelopmentInformation-tzKaZHafsX2t","type":"http://ontosoft.org/software#DevelopmentInformation","value":"https://github.com/ropensci/taxizedb"}],"http://ontosoft.org/software#hasAdopter":[],"http://ontosoft.org/software#hasAverageRunTime":[],"http://ontosoft.org/software#hasBenchmarkInformation":[],"http://ontosoft.org/software#hasCodeLocation":[{"@type":"Location","id":"http://imcr.ontosoft.org/repository/software/Software-rNPaVbUcYRkB#Location-43CcCZRzvV5S","name":"Location-43CcCZRzvV5S","type":"http://ontosoft.org/software#Location","value":"https://cran.r-project.org/web/packages/taxizedb/index.html"}],"http://ontosoft.org/software#hasCommitmentOfSupport":[{"@type":"TextEntity","id":"http://imcr.ontosoft.org/repository/software/Software-rNPaVbUcYRkB#TextEntity-TsuuCuHWTOiF","name":"TextEntity-TsuuCuHWTOiF","type":"http://ontosoft.org/software#TextEntity","value":"https://github.com/ropensci/taxizedb/issues"}],"http://ontosoft.org/software#hasCompositionDescription":[],"http://ontosoft.org/software#hasCreator":[{"@type":"EnumerationEntity","id":"http://imcr.ontosoft.org/repository/software/enumerations#Agent-RpFZdQFcvvCQ","name":"Agent-RpFZdQFcvvCQ","type":"http://www.w3.org/ns/prov#Agent","label":"Scott Chamberlain","value":"Scott Chamberlain"}],"http://ontosoft.org/software#hasDependency":[],"http://ontosoft.org/software#hasDocumentation":[{"@type":"Location","id":"http://imcr.ontosoft.org/repository/software/Software-rNPaVbUcYRkB#Location-wTD3JUYtb0Kt","name":"Location-wTD3JUYtb0Kt","type":"http://ontosoft.org/software#Location","value":"https://cran.r-project.org/web/packages/taxizedb/taxizedb.pdf"}],"http://ontosoft.org/software#hasDomainKeywords":[],"http://ontosoft.org/software#hasEmailContact":[],"http://ontosoft.org/software#hasExecutableLocation":[],"http://ontosoft.org/software#hasFundingSources":[],"http://ontosoft.org/software#hasImplementationLanguage":[{"@type":"EnumerationEntity","id":"http://imcr.ontosoft.org/repository/software/enumerations#ProgrammingLanguage-Tkrq9BFxdt0O","name":"ProgrammingLanguage-Tkrq9BFxdt0O","type":"http://ontosoft.org/software#ProgrammingLanguage","label":"R","value":"R"}],"http://ontosoft.org/software#hasInput":[],"http://ontosoft.org/software#hasInputParameter":[],"http://ontosoft.org/software#hasInstallationInstructions":[],"http://ontosoft.org/software#hasInteroperableSoftware":[],"http://ontosoft.org/software#hasLicense":[{"@type":"EnumerationEntity","id":"http://ontosoft.org/software#MIT","name":"MIT","type":"http://ontosoft.org/software#License","label":"MIT License","value":"MIT License"}],"http://ontosoft.org/software#hasMajorContributor":[],"http://ontosoft.org/software#hasName":[{"@type":"TextEntity","id":"http://imcr.ontosoft.org/repository/software/Software-rNPaVbUcYRkB#TextEntity-Nz4rYi2srXXE","name":"TextEntity-Nz4rYi2srXXE","type":"http://ontosoft.org/software#TextEntity","value":"taxizedb"}],"http://ontosoft.org/software#hasOtherImplementationDetails":[],"http://ontosoft.org/software#hasOutput":[],"http://ontosoft.org/software#hasPreferredCitation":[],"http://ontosoft.org/software#hasProjectWebsite":[{"@type":"Location","id":"http://imcr.ontosoft.org/repository/software/Software-rNPaVbUcYRkB#Location-qeevylYL81jW","name":"Location-qeevylYL81jW","type":"http://ontosoft.org/software#Location","value":"https://github.com/ropensci/taxizedb"}],"http://ontosoft.org/software#hasPublisher":[{"@type":"EnumerationEntity","id":"http://imcr.ontosoft.org/repository/software/enumerations#Publisher-0k3Oz3jsbwPn","name":"Publisher-0k3Oz3jsbwPn","type":"http://ontosoft.org/software#Publisher","label":"CRAN","value":"CRAN"}],"http://ontosoft.org/software#hasRating":[],"http://ontosoft.org/software#hasRelevantDataSources":[],"http://ontosoft.org/software#hasSalientQualities":[],"http://ontosoft.org/software#hasShortDescription":[{"@type":"TextEntity","id":"http://imcr.ontosoft.org/repository/software/Software-rNPaVbUcYRkB#TextEntity-pW5WecKuscwL","name":"TextEntity-pW5WecKuscwL","type":"http://ontosoft.org/software#TextEntity","value":"Tools for working with 'taxonomic' databases, including utilities for downloading databases, loading them into various 'SQL' databases, cleaning up files, and providing a 'SQL' connection that can be used to do 'SQL' queries directly or used in 'dplyr'."}],"http://ontosoft.org/software#hasSoftwareCategory":[{"@type":"EnumerationEntity","id":"http://imcr.ontosoft.org/repository/software/enumerations#SoftwareCategory-gtib5Wlg3FGZ","name":"SoftwareCategory-gtib5Wlg3FGZ","type":"http://ontosoft.org/software#SoftwareCategory","label":"quality control","value":"quality control"},{"@type":"EnumerationEntity","id":"http://imcr.ontosoft.org/repository/software/enumerations#SoftwareCategory-02I2h7spnEo2","name":"SoftwareCategory-02I2h7spnEo2","type":"http://ontosoft.org/software#SoftwareCategory","label":"describing","value":"describing"},{"@type":"EnumerationEntity","id":"http://imcr.ontosoft.org/repository/software/enumerations#SoftwareCategory-ETibAfFmiTaD","name":"SoftwareCategory-ETibAfFmiTaD","type":"http://ontosoft.org/software#SoftwareCategory","label":"integration","value":"integration"},{"@type":"EnumerationEntity","id":"http://imcr.ontosoft.org/repository/software/enumerations#SoftwareCategory-BhrsPrEIoumc","name":"SoftwareCategory-BhrsPrEIoumc","type":"http://ontosoft.org/software#SoftwareCategory","label":"validation","value":"validation"},{"@type":"EnumerationEntity","id":"http://imcr.ontosoft.org/repository/software/enumerations#SoftwareCategory-bR7VLgRGWmaC","name":"SoftwareCategory-bR7VLgRGWmaC","type":"http://ontosoft.org/software#SoftwareCategory","label":"assurance","value":"assurance"}],"http://ontosoft.org/software#hasSoftwareCommunity":[{"@type":"TextEntity","id":"http://imcr.ontosoft.org/repository/software/Software-rNPaVbUcYRkB#CommunityInformation-hHFXr6otTTQd","name":"CommunityInformation-hHFXr6otTTQd","type":"http://ontosoft.org/software#CommunityInformation","value":"https://github.com/ropensci/taxizedb"}],"http://ontosoft.org/software#hasSoftwareSupport":[{"@type":"TextEntity","id":"http://imcr.ontosoft.org/repository/software/Software-rNPaVbUcYRkB#TextEntity-jghDDrddgECw","name":"TextEntity-jghDDrddgECw","type":"http://ontosoft.org/software#TextEntity","value":"https://github.com/ropensci/taxizedb"}],"http://ontosoft.org/software#hasSoftwareVersion":[],"http://ontosoft.org/software#hasTestData":[],"http://ontosoft.org/software#hasTestInstructions":[],"http://ontosoft.org/software#hasUniqueId":[],"http://ontosoft.org/software#hasUsageInformation":[],"http://ontosoft.org/software#hasUseLimitations":[],"http://ontosoft.org/software#hasUseStatistics":[],"http://ontosoft.org/software#hasUsesAndAssumptions":[],"http://ontosoft.org/software#requiresAverageMemory":[],"http://ontosoft.org/software#similarSoftware":[],"http://ontosoft.org/software#supportsOperatingSystem":[],"http://ontosoft.org/software#usedInPublication":[]},"provenance":{"id":"http://imcr.ontosoft.org/repository/software/Software-rNPaVbUcYRkB/provenance","entities":{"http://imcr.ontosoft.org/repository/software/Software-rNPaVbUcYRkB":{"id":"http://imcr.ontosoft.org/repository/software/Software-rNPaVbUcYRkB","revisionOf":{},"generatedBy":"http://imcr.ontosoft.org/repository/software/Software-rNPaVbUcYRkB/provenance#Create-5KcMGl53Lmhz","invalidatedBy":{}},"http://imcr.ontosoft.org/repository/software/enumerations#SoftwareCategory-02I2h7spnEo2":{"id":"http://imcr.ontosoft.org/repository/software/enumerations#SoftwareCategory-02I2h7spnEo2","revisionOf":{},"generatedBy":"http://imcr.ontosoft.org/repository/software/Software-rNPaVbUcYRkB/provenance#Update-8pWtPeCO093B","invalidatedBy":{}},"http://imcr.ontosoft.org/repository/software/enumerations#SoftwareCategory-ETibAfFmiTaD":{"id":"http://imcr.ontosoft.org/repository/software/enumerations#SoftwareCategory-ETibAfFmiTaD","revisionOf":{},"generatedBy":"http://imcr.ontosoft.org/repository/software/Software-rNPaVbUcYRkB/provenance#Update-8pWtPeCO093B","invalidatedBy":{}},"http://imcr.ontosoft.org/repository/software/enumerations#SoftwareCategory-BhrsPrEIoumc":{"id":"http://imcr.ontosoft.org/repository/software/enumerations#SoftwareCategory-BhrsPrEIoumc","revisionOf":{},"generatedBy":"http://imcr.ontosoft.org/repository/software/Software-rNPaVbUcYRkB/provenance#Update-8pWtPeCO093B","invalidatedBy":{}},"http://imcr.ontosoft.org/repository/software/enumerations#Publisher-0k3Oz3jsbwPn":{"id":"http://imcr.ontosoft.org/repository/software/enumerations#Publisher-0k3Oz3jsbwPn","revisionOf":{},"generatedBy":"http://imcr.ontosoft.org/repository/software/Software-rNPaVbUcYRkB/provenance#Update-8pWtPeCO093B","invalidatedBy":{}},"http://imcr.ontosoft.org/repository/software/Software-rNPaVbUcYRkB#TextEntity-TsuuCuHWTOiF":{"id":"http://imcr.ontosoft.org/repository/software/Software-rNPaVbUcYRkB#TextEntity-TsuuCuHWTOiF","revisionOf":{},"generatedBy":"http://imcr.ontosoft.org/repository/software/Software-rNPaVbUcYRkB/provenance#Update-8pWtPeCO093B","invalidatedBy":{}},"http://imcr.ontosoft.org/repository/software/Software-rNPaVbUcYRkB#Location-qeevylYL81jW":{"id":"http://imcr.ontosoft.org/repository/software/Software-rNPaVbUcYRkB#Location-qeevylYL81jW","revisionOf":{},"generatedBy":"http://imcr.ontosoft.org/repository/software/Software-rNPaVbUcYRkB/provenance#Update-8pWtPeCO093B","invalidatedBy":{}},"http://imcr.ontosoft.org/repository/software/enumerations#ProgrammingLanguage-Tkrq9BFxdt0O":{"id":"http://imcr.ontosoft.org/repository/software/enumerations#ProgrammingLanguage-Tkrq9BFxdt0O","revisionOf":{},"generatedBy":"http://imcr.ontosoft.org/repository/software/Software-rNPaVbUcYRkB/provenance#Update-8pWtPeCO093B","invalidatedBy":{}},"http://imcr.ontosoft.org/repository/software/enumerations#SoftwareCategory-JU2mTDIbvdNc":{"id":"http://imcr.ontosoft.org/repository/software/enumerations#SoftwareCategory-JU2mTDIbvdNc","revisionOf":{},"generatedBy":"http://imcr.ontosoft.org/repository/software/Software-rNPaVbUcYRkB/provenance#Update-8pWtPeCO093B","invalidatedBy":"http://imcr.ontosoft.org/repository/software/Software-rNPaVbUcYRkB/provenance#Update-MWf0uFdfA8DL"},"http://imcr.ontosoft.org/repository/software/Software-rNPaVbUcYRkB#CommunityInformation-hHFXr6otTTQd":{"id":"http://imcr.ontosoft.org/repository/software/Software-rNPaVbUcYRkB#CommunityInformation-hHFXr6otTTQd","revisionOf":{},"generatedBy":"http://imcr.ontosoft.org/repository/software/Software-rNPaVbUcYRkB/provenance#Update-8pWtPeCO093B","invalidatedBy":{}},"http://ontosoft.org/software#MIT":{"id":"http://ontosoft.org/software#MIT","revisionOf":{},"generatedBy":"http://imcr.ontosoft.org/repository/software/Software-rNPaVbUcYRkB/provenance#Update-8pWtPeCO093B","invalidatedBy":{}},"http://imcr.ontosoft.org/repository/software/Software-rNPaVbUcYRkB#DevelopmentInformation-tzKaZHafsX2t":{"id":"http://imcr.ontosoft.org/repository/software/Software-rNPaVbUcYRkB#DevelopmentInformation-tzKaZHafsX2t","revisionOf":{},"generatedBy":"http://imcr.ontosoft.org/repository/software/Software-rNPaVbUcYRkB/provenance#Update-8pWtPeCO093B","invalidatedBy":{}},"http://imcr.ontosoft.org/repository/software/enumerations#SoftwareCategory-bR7VLgRGWmaC":{"id":"http://imcr.ontosoft.org/repository/software/enumerations#SoftwareCategory-bR7VLgRGWmaC","revisionOf":{},"generatedBy":"http://imcr.ontosoft.org/repository/software/Software-rNPaVbUcYRkB/provenance#Update-8pWtPeCO093B","invalidatedBy":{}},"http://imcr.ontosoft.org/repository/software/Software-rNPaVbUcYRkB#TextEntity-jghDDrddgECw":{"id":"http://imcr.ontosoft.org/repository/software/Software-rNPaVbUcYRkB#TextEntity-jghDDrddgECw","revisionOf":{},"generatedBy":"http://imcr.ontosoft.org/repository/software/Software-rNPaVbUcYRkB/provenance#Update-8pWtPeCO093B","invalidatedBy":{}},"http://imcr.ontosoft.org/repository/software/Software-rNPaVbUcYRkB#Location-43CcCZRzvV5S":{"id":"http://imcr.ontosoft.org/repository/software/Software-rNPaVbUcYRkB#Location-43CcCZRzvV5S","revisionOf":{},"generatedBy":"http://imcr.ontosoft.org/repository/software/Software-rNPaVbUcYRkB/provenance#Update-8pWtPeCO093B","invalidatedBy":{}},"http://imcr.ontosoft.org/repository/software/Software-rNPaVbUcYRkB#TextEntity-Nz4rYi2srXXE":{"id":"http://imcr.ontosoft.org/repository/software/Software-rNPaVbUcYRkB#TextEntity-Nz4rYi2srXXE","revisionOf":{},"generatedBy":"http://imcr.ontosoft.org/repository/software/Software-rNPaVbUcYRkB/provenance#Update-8pWtPeCO093B","invalidatedBy":{}},"http://imcr.ontosoft.org/repository/software/enumerations#Agent-RpFZdQFcvvCQ":{"id":"http://imcr.ontosoft.org/repository/software/enumerations#Agent-RpFZdQFcvvCQ","revisionOf":{},"generatedBy":"http://imcr.ontosoft.org/repository/software/Software-rNPaVbUcYRkB/provenance#Update-8pWtPeCO093B","invalidatedBy":{}},"http://imcr.ontosoft.org/repository/software/Software-rNPaVbUcYRkB#Location-wTD3JUYtb0Kt":{"id":"http://imcr.ontosoft.org/repository/software/Software-rNPaVbUcYRkB#Location-wTD3JUYtb0Kt","revisionOf":{},"generatedBy":"http://imcr.ontosoft.org/repository/software/Software-rNPaVbUcYRkB/provenance#Update-8pWtPeCO093B","invalidatedBy":{}},"http://imcr.ontosoft.org/repository/software/enumerations#SoftwareCategory-gtib5Wlg3FGZ":{"id":"http://imcr.ontosoft.org/repository/software/enumerations#SoftwareCategory-gtib5Wlg3FGZ","revisionOf":{},"generatedBy":"http://imcr.ontosoft.org/repository/software/Software-rNPaVbUcYRkB/provenance#Update-8pWtPeCO093B","invalidatedBy":{}},"http://imcr.ontosoft.org/repository/software/Software-rNPaVbUcYRkB#TextEntity-pW5WecKuscwL":{"id":"http://imcr.ontosoft.org/repository/software/Software-rNPaVbUcYRkB#TextEntity-pW5WecKuscwL","revisionOf":{},"generatedBy":"http://imcr.ontosoft.org/repository/software/Software-rNPaVbUcYRkB/provenance#Update-8pWtPeCO093B","invalidatedBy":{}}},"activities":{"http://imcr.ontosoft.org/repository/software/Software-rNPaVbUcYRkB/provenance#Create-5KcMGl53Lmhz":{"id":"http://imcr.ontosoft.org/repository/software/Software-rNPaVbUcYRkB/provenance#Create-5KcMGl53Lmhz","time":1552681978859,"agentId":"http://imcr.ontosoft.org/repository/users/csmith"},"http://imcr.ontosoft.org/repository/software/Software-rNPaVbUcYRkB/provenance#Update-8pWtPeCO093B":{"id":"http://imcr.ontosoft.org/repository/software/Software-rNPaVbUcYRkB/provenance#Update-8pWtPeCO093B","time":1552682300730,"agentId":"http://imcr.ontosoft.org/repository/users/csmith"},"http://imcr.ontosoft.org/repository/software/Software-rNPaVbUcYRkB/provenance#Update-MWf0uFdfA8DL":{"id":"http://imcr.ontosoft.org/repository/software/Software-rNPaVbUcYRkB/provenance#Update-MWf0uFdfA8DL","time":1562900873117,"agentId":"http://imcr.ontosoft.org/repository/users/csmith"}},"agents":{"http://imcr.ontosoft.org/repository/users/csmith":{"id":"http://imcr.ontosoft.org/repository/users/csmith","name":"csmith"}}},"permission":{"id":"http://imcr.ontosoft.org/repository/software/Software-rNPaVbUcYRkB/permission","owners":[{"id":"http://imcr.ontosoft.org/repository/users/csmith"}],"type":{},"authorizations":{"http://imcr.ontosoft.org/repository/software/Software-rNPaVbUcYRkB/permission#Auth-6ZSxiQNlQzAn":{"id":"http://imcr.ontosoft.org/repository/software/Software-rNPaVbUcYRkB/permission#Auth-6ZSxiQNlQzAn","agentId":"http://imcr.ontosoft.org/repository/users/csmith","agentName":"csmith","accessMode":{"id":"http://www.w3.org/ns/auth/acl#Write","mode":"Write"},"accessToObjId":"http://imcr.ontosoft.org/repository/software/Software-rNPaVbUcYRkB"}}}}
