{"@type":"Software","id":"http://imcr.ontosoft.org/repository/software/Software-WdfIVRh64DEj","name":"Software-WdfIVRh64DEj","type":"http://ontosoft.org/software#Software","label":"antiword","value":{"http://ontosoft.org/software#hasActiveDevelopment":[{"@type":"TextEntity","id":"http://imcr.ontosoft.org/repository/software/Software-WdfIVRh64DEj#DevelopmentInformation-3cxnkqdwBWj3","name":"DevelopmentInformation-3cxnkqdwBWj3","type":"http://ontosoft.org/software#DevelopmentInformation","value":"https://github.com/ropensci/antiword"}],"http://ontosoft.org/software#hasAdopter":[],"http://ontosoft.org/software#hasAverageRunTime":[],"http://ontosoft.org/software#hasBenchmarkInformation":[],"http://ontosoft.org/software#hasCodeLocation":[{"@type":"Location","id":"http://imcr.ontosoft.org/repository/software/Software-WdfIVRh64DEj#Location-g5qWM9SBgKcV","name":"Location-g5qWM9SBgKcV","type":"http://ontosoft.org/software#Location","value":"https://cran.r-project.org/web/packages/antiword/index.html"}],"http://ontosoft.org/software#hasCommitmentOfSupport":[{"@type":"TextEntity","id":"http://imcr.ontosoft.org/repository/software/Software-WdfIVRh64DEj#TextEntity-XuJyRSJ43dkn","name":"TextEntity-XuJyRSJ43dkn","type":"http://ontosoft.org/software#TextEntity","value":"https://github.com/ropensci/antiword/issues"}],"http://ontosoft.org/software#hasCompositionDescription":[],"http://ontosoft.org/software#hasCreator":[{"@type":"EnumerationEntity","id":"http://imcr.ontosoft.org/repository/software/enumerations#Agent-TULQzLS4FSbh","name":"Agent-TULQzLS4FSbh","type":"http://www.w3.org/ns/prov#Agent","label":"Jeroen Ooms","value":"Jeroen Ooms"}],"http://ontosoft.org/software#hasDependency":[],"http://ontosoft.org/software#hasDocumentation":[{"@type":"Location","id":"http://imcr.ontosoft.org/repository/software/Software-WdfIVRh64DEj#Location-hzpDHUGkKCdx","name":"Location-hzpDHUGkKCdx","type":"http://ontosoft.org/software#Location","value":"https://cran.r-project.org/web/packages/antiword/antiword.pdf"}],"http://ontosoft.org/software#hasDomainKeywords":[],"http://ontosoft.org/software#hasEmailContact":[],"http://ontosoft.org/software#hasExecutableLocation":[],"http://ontosoft.org/software#hasFundingSources":[],"http://ontosoft.org/software#hasImplementationLanguage":[{"@type":"EnumerationEntity","id":"http://imcr.ontosoft.org/repository/software/enumerations#ProgrammingLanguage-Tkrq9BFxdt0O","name":"ProgrammingLanguage-Tkrq9BFxdt0O","type":"http://ontosoft.org/software#ProgrammingLanguage","label":"R","value":"R"}],"http://ontosoft.org/software#hasInput":[],"http://ontosoft.org/software#hasInputParameter":[],"http://ontosoft.org/software#hasInstallationInstructions":[{"@type":"TextEntity","id":"http://imcr.ontosoft.org/repository/software/Software-WdfIVRh64DEj#TextEntity-RdRKy24jP3Av","name":"TextEntity-RdRKy24jP3Av","type":"http://ontosoft.org/software#TextEntity","value":"install.packages('antiword')"}],"http://ontosoft.org/software#hasInteroperableSoftware":[],"http://ontosoft.org/software#hasLicense":[{"@type":"EnumerationEntity","id":"http://imcr.ontosoft.org/repository/software/enumerations#License-qCP5R777MVwz","name":"License-qCP5R777MVwz","type":"http://ontosoft.org/software#License","label":"GPLv2 license","value":"GPLv2 license"}],"http://ontosoft.org/software#hasMajorContributor":[],"http://ontosoft.org/software#hasName":[{"@type":"TextEntity","id":"http://imcr.ontosoft.org/repository/software/Software-WdfIVRh64DEj#TextEntity-yg0S1QqTyvVw","name":"TextEntity-yg0S1QqTyvVw","type":"http://ontosoft.org/software#TextEntity","value":"antiword"}],"http://ontosoft.org/software#hasOtherImplementationDetails":[],"http://ontosoft.org/software#hasOutput":[],"http://ontosoft.org/software#hasPreferredCitation":[],"http://ontosoft.org/software#hasProjectWebsite":[{"@type":"Location","id":"http://imcr.ontosoft.org/repository/software/Software-WdfIVRh64DEj#Location-Zl4fxREIyHyv","name":"Location-Zl4fxREIyHyv","type":"http://ontosoft.org/software#Location","value":"https://github.com/ropensci/antiword"}],"http://ontosoft.org/software#hasPublisher":[{"@type":"EnumerationEntity","id":"http://imcr.ontosoft.org/repository/software/enumerations#Publisher-0k3Oz3jsbwPn","name":"Publisher-0k3Oz3jsbwPn","type":"http://ontosoft.org/software#Publisher","label":"CRAN","value":"CRAN"}],"http://ontosoft.org/software#hasRating":[],"http://ontosoft.org/software#hasRelevantDataSources":[],"http://ontosoft.org/software#hasSalientQualities":[],"http://ontosoft.org/software#hasShortDescription":[{"@type":"TextEntity","id":"http://imcr.ontosoft.org/repository/software/Software-WdfIVRh64DEj#TextEntity-vEAxDL016Zqh","name":"TextEntity-vEAxDL016Zqh","type":"http://ontosoft.org/software#TextEntity","value":"Wraps the AntiWord utility to extract text from Microsoft Word documents. The utility only supports the old doc format, not the new xml based docx format."}],"http://ontosoft.org/software#hasSoftwareCategory":[{"@type":"EnumerationEntity","id":"http://imcr.ontosoft.org/repository/software/enumerations#SoftwareCategory-ETibAfFmiTaD","name":"SoftwareCategory-ETibAfFmiTaD","type":"http://ontosoft.org/software#SoftwareCategory","label":"integration","value":"integration"},{"@type":"EnumerationEntity","id":"http://imcr.ontosoft.org/repository/software/enumerations#SoftwareCategory-iv3CRCoVO8Ad","name":"SoftwareCategory-iv3CRCoVO8Ad","type":"http://ontosoft.org/software#SoftwareCategory","label":"conversion","value":"conversion"},{"@type":"EnumerationEntity","id":"http://imcr.ontosoft.org/repository/software/enumerations#SoftwareCategory-VikpybShWY9p","name":"SoftwareCategory-VikpybShWY9p","type":"http://ontosoft.org/software#SoftwareCategory","label":"transformation","value":"transformation"},{"@type":"EnumerationEntity","id":"http://imcr.ontosoft.org/repository/software/enumerations#SoftwareCategory-Qeazp4KGtVSq","name":"SoftwareCategory-Qeazp4KGtVSq","type":"http://ontosoft.org/software#SoftwareCategory","label":"formatting","value":"formatting"}],"http://ontosoft.org/software#hasSoftwareCommunity":[{"@type":"TextEntity","id":"http://imcr.ontosoft.org/repository/software/Software-WdfIVRh64DEj#CommunityInformation-2JGSCcnncjw5","name":"CommunityInformation-2JGSCcnncjw5","type":"http://ontosoft.org/software#CommunityInformation","value":"https://github.com/ropensci/antiword"}],"http://ontosoft.org/software#hasSoftwareSupport":[{"@type":"TextEntity","id":"http://imcr.ontosoft.org/repository/software/Software-WdfIVRh64DEj#TextEntity-m9aWjrrPF9Pd","name":"TextEntity-m9aWjrrPF9Pd","type":"http://ontosoft.org/software#TextEntity","value":"https://github.com/ropensci/antiword"}],"http://ontosoft.org/software#hasSoftwareVersion":[],"http://ontosoft.org/software#hasTestData":[],"http://ontosoft.org/software#hasTestInstructions":[],"http://ontosoft.org/software#hasUniqueId":[],"http://ontosoft.org/software#hasUsageInformation":[],"http://ontosoft.org/software#hasUseLimitations":[],"http://ontosoft.org/software#hasUseStatistics":[],"http://ontosoft.org/software#hasUsesAndAssumptions":[],"http://ontosoft.org/software#requiresAverageMemory":[],"http://ontosoft.org/software#similarSoftware":[],"http://ontosoft.org/software#supportsOperatingSystem":[],"http://ontosoft.org/software#usedInPublication":[]},"provenance":{"id":"http://imcr.ontosoft.org/repository/software/Software-WdfIVRh64DEj/provenance","entities":{"http://imcr.ontosoft.org/repository/software/Software-WdfIVRh64DEj#TextEntity-vEAxDL016Zqh":{"id":"http://imcr.ontosoft.org/repository/software/Software-WdfIVRh64DEj#TextEntity-vEAxDL016Zqh","revisionOf":{},"generatedBy":"http://imcr.ontosoft.org/repository/software/Software-WdfIVRh64DEj/provenance#Update-5Ijbt2269UVX","invalidatedBy":{}},"http://imcr.ontosoft.org/repository/software/enumerations#Agent-TULQzLS4FSbh":{"id":"http://imcr.ontosoft.org/repository/software/enumerations#Agent-TULQzLS4FSbh","revisionOf":{},"generatedBy":"http://imcr.ontosoft.org/repository/software/Software-WdfIVRh64DEj/provenance#Update-NZe7z0ebPuIZ","invalidatedBy":{}},"http://imcr.ontosoft.org/repository/software/enumerations#SoftwareCategory-rCgSFJqKWGtr":{"id":"http://imcr.ontosoft.org/repository/software/enumerations#SoftwareCategory-rCgSFJqKWGtr","revisionOf":{},"generatedBy":"http://imcr.ontosoft.org/repository/software/Software-WdfIVRh64DEj/provenance#Update-5Ijbt2269UVX","invalidatedBy":{}},"http://imcr.ontosoft.org/repository/software/enumerations#SoftwareCategory-ETibAfFmiTaD":{"id":"http://imcr.ontosoft.org/repository/software/enumerations#SoftwareCategory-ETibAfFmiTaD","revisionOf":{},"generatedBy":"http://imcr.ontosoft.org/repository/software/Software-WdfIVRh64DEj/provenance#Update-5Ijbt2269UVX","invalidatedBy":{}},"http://imcr.ontosoft.org/repository/software/Software-WdfIVRh64DEj#TextEntity-yg0S1QqTyvVw":{"id":"http://imcr.ontosoft.org/repository/software/Software-WdfIVRh64DEj#TextEntity-yg0S1QqTyvVw","revisionOf":{},"generatedBy":"http://imcr.ontosoft.org/repository/software/Software-WdfIVRh64DEj/provenance#Update-5Ijbt2269UVX","invalidatedBy":{}},"http://imcr.ontosoft.org/repository/software/Software-WdfIVRh64DEj#Location-g5qWM9SBgKcV":{"id":"http://imcr.ontosoft.org/repository/software/Software-WdfIVRh64DEj#Location-g5qWM9SBgKcV","revisionOf":{},"generatedBy":"http://imcr.ontosoft.org/repository/software/Software-WdfIVRh64DEj/provenance#Update-WF1eDsUb238I","invalidatedBy":{}},"http://imcr.ontosoft.org/repository/software/Software-WdfIVRh64DEj#TextEntity-RdRKy24jP3Av":{"id":"http://imcr.ontosoft.org/repository/software/Software-WdfIVRh64DEj#TextEntity-RdRKy24jP3Av","revisionOf":{},"generatedBy":"http://imcr.ontosoft.org/repository/software/Software-WdfIVRh64DEj/provenance#Update-WF1eDsUb238I","invalidatedBy":{}},"http://imcr.ontosoft.org/repository/software/Software-WdfIVRh64DEj#TextEntity-m9aWjrrPF9Pd":{"id":"http://imcr.ontosoft.org/repository/software/Software-WdfIVRh64DEj#TextEntity-m9aWjrrPF9Pd","revisionOf":{},"generatedBy":"http://imcr.ontosoft.org/repository/software/Software-WdfIVRh64DEj/provenance#Update-WF1eDsUb238I","invalidatedBy":{}},"http://imcr.ontosoft.org/repository/software/enumerations#Publisher-0k3Oz3jsbwPn":{"id":"http://imcr.ontosoft.org/repository/software/enumerations#Publisher-0k3Oz3jsbwPn","revisionOf":{},"generatedBy":"http://imcr.ontosoft.org/repository/software/Software-WdfIVRh64DEj/provenance#Update-NZe7z0ebPuIZ","invalidatedBy":{}},"http://imcr.ontosoft.org/repository/software/Software-WdfIVRh64DEj#CommunityInformation-2JGSCcnncjw5":{"id":"http://imcr.ontosoft.org/repository/software/Software-WdfIVRh64DEj#CommunityInformation-2JGSCcnncjw5","revisionOf":{},"generatedBy":"http://imcr.ontosoft.org/repository/software/Software-WdfIVRh64DEj/provenance#Update-WF1eDsUb238I","invalidatedBy":{}},"http://imcr.ontosoft.org/repository/software/enumerations#ProgrammingLanguage-Tkrq9BFxdt0O":{"id":"http://imcr.ontosoft.org/repository/software/enumerations#ProgrammingLanguage-Tkrq9BFxdt0O","revisionOf":{},"generatedBy":"http://imcr.ontosoft.org/repository/software/Software-WdfIVRh64DEj/provenance#Update-WF1eDsUb238I","invalidatedBy":{}},"http://imcr.ontosoft.org/repository/software/Software-WdfIVRh64DEj#SoftwareCategory-xsycKmUqfoW5":{"id":"http://imcr.ontosoft.org/repository/software/Software-WdfIVRh64DEj#SoftwareCategory-xsycKmUqfoW5","revisionOf":"http://imcr.ontosoft.org/repository/software/enumerations#SoftwareCategory-rCgSFJqKWGtr","generatedBy":"http://imcr.ontosoft.org/repository/software/Software-WdfIVRh64DEj/provenance#Update-1a1kSddpvMcR","invalidatedBy":{}},"http://imcr.ontosoft.org/repository/software/Software-WdfIVRh64DEj#TextEntity-XuJyRSJ43dkn":{"id":"http://imcr.ontosoft.org/repository/software/Software-WdfIVRh64DEj#TextEntity-XuJyRSJ43dkn","revisionOf":{},"generatedBy":"http://imcr.ontosoft.org/repository/software/Software-WdfIVRh64DEj/provenance#Update-NZe7z0ebPuIZ","invalidatedBy":{}},"http://imcr.ontosoft.org/repository/software/Software-WdfIVRh64DEj#Location-Zl4fxREIyHyv":{"id":"http://imcr.ontosoft.org/repository/software/Software-WdfIVRh64DEj#Location-Zl4fxREIyHyv","revisionOf":{},"generatedBy":"http://imcr.ontosoft.org/repository/software/Software-WdfIVRh64DEj/provenance#Update-5Ijbt2269UVX","invalidatedBy":{}},"http://imcr.ontosoft.org/repository/software/Software-WdfIVRh64DEj#License-Vytzsx5fqbII":{"id":"http://imcr.ontosoft.org/repository/software/Software-WdfIVRh64DEj#License-Vytzsx5fqbII","revisionOf":{},"generatedBy":"http://imcr.ontosoft.org/repository/software/Software-WdfIVRh64DEj/provenance#Update-WF1eDsUb238I","invalidatedBy":{}},"http://imcr.ontosoft.org/repository/software/enumerations#SoftwareCategory-iv3CRCoVO8Ad":{"id":"http://imcr.ontosoft.org/repository/software/enumerations#SoftwareCategory-iv3CRCoVO8Ad","revisionOf":{},"generatedBy":"http://imcr.ontosoft.org/repository/software/Software-WdfIVRh64DEj/provenance#Update-5Ijbt2269UVX","invalidatedBy":{}},"http://imcr.ontosoft.org/repository/software/Software-WdfIVRh64DEj":{"id":"http://imcr.ontosoft.org/repository/software/Software-WdfIVRh64DEj","revisionOf":{},"generatedBy":"http://imcr.ontosoft.org/repository/software/Software-WdfIVRh64DEj/provenance#Create-jNRdVuXnTG80","invalidatedBy":{}},"http://imcr.ontosoft.org/repository/software/enumerations#SoftwareCategory-VikpybShWY9p":{"id":"http://imcr.ontosoft.org/repository/software/enumerations#SoftwareCategory-VikpybShWY9p","revisionOf":{},"generatedBy":"http://imcr.ontosoft.org/repository/software/Software-WdfIVRh64DEj/provenance#Update-5Ijbt2269UVX","invalidatedBy":{}},"http://imcr.ontosoft.org/repository/software/Software-WdfIVRh64DEj#Location-hzpDHUGkKCdx":{"id":"http://imcr.ontosoft.org/repository/software/Software-WdfIVRh64DEj#Location-hzpDHUGkKCdx","revisionOf":{},"generatedBy":"http://imcr.ontosoft.org/repository/software/Software-WdfIVRh64DEj/provenance#Update-WF1eDsUb238I","invalidatedBy":{}},"http://imcr.ontosoft.org/repository/software/Software-WdfIVRh64DEj#DevelopmentInformation-3cxnkqdwBWj3":{"id":"http://imcr.ontosoft.org/repository/software/Software-WdfIVRh64DEj#DevelopmentInformation-3cxnkqdwBWj3","revisionOf":{},"generatedBy":"http://imcr.ontosoft.org/repository/software/Software-WdfIVRh64DEj/provenance#Update-WF1eDsUb238I","invalidatedBy":{}}},"activities":{"http://imcr.ontosoft.org/repository/software/Software-WdfIVRh64DEj/provenance#Create-jNRdVuXnTG80":{"id":"http://imcr.ontosoft.org/repository/software/Software-WdfIVRh64DEj/provenance#Create-jNRdVuXnTG80","time":1551898224554,"agentId":"http://imcr.ontosoft.org/repository/users/csmith"},"http://imcr.ontosoft.org/repository/software/Software-WdfIVRh64DEj/provenance#Update-WF1eDsUb238I":{"id":"http://imcr.ontosoft.org/repository/software/Software-WdfIVRh64DEj/provenance#Update-WF1eDsUb238I","time":1551898517022,"agentId":"http://imcr.ontosoft.org/repository/users/csmith"},"http://imcr.ontosoft.org/repository/software/Software-WdfIVRh64DEj/provenance#Update-1a1kSddpvMcR":{"id":"http://imcr.ontosoft.org/repository/software/Software-WdfIVRh64DEj/provenance#Update-1a1kSddpvMcR","time":1562900370903,"agentId":"http://imcr.ontosoft.org/repository/users/csmith"},"http://imcr.ontosoft.org/repository/software/Software-WdfIVRh64DEj/provenance#Update-5Ijbt2269UVX":{"id":"http://imcr.ontosoft.org/repository/software/Software-WdfIVRh64DEj/provenance#Update-5Ijbt2269UVX","time":1551898325458,"agentId":"http://imcr.ontosoft.org/repository/users/csmith"},"http://imcr.ontosoft.org/repository/software/Software-WdfIVRh64DEj/provenance#Update-NZe7z0ebPuIZ":{"id":"http://imcr.ontosoft.org/repository/software/Software-WdfIVRh64DEj/provenance#Update-NZe7z0ebPuIZ","time":1551898412337,"agentId":"http://imcr.ontosoft.org/repository/users/csmith"}},"agents":{"http://imcr.ontosoft.org/repository/users/csmith":{"id":"http://imcr.ontosoft.org/repository/users/csmith","name":"csmith"}}},"permission":{"id":"http://imcr.ontosoft.org/repository/software/Software-WdfIVRh64DEj/permission","owners":[{"id":"http://imcr.ontosoft.org/repository/users/csmith"}],"type":{},"authorizations":{"http://imcr.ontosoft.org/repository/software/Software-WdfIVRh64DEj/permission#Auth-VH0OzWO08I79":{"id":"http://imcr.ontosoft.org/repository/software/Software-WdfIVRh64DEj/permission#Auth-VH0OzWO08I79","agentId":"http://imcr.ontosoft.org/repository/users/csmith","agentName":"csmith","accessMode":{"id":"http://www.w3.org/ns/auth/acl#Write","mode":"Write"},"accessToObjId":"http://imcr.ontosoft.org/repository/software/Software-WdfIVRh64DEj"}}}}
