{"@type":"Software","id":"http://imcr.ontosoft.org/repository/software/Software-eAtWf4v4fDb2","name":"Software-eAtWf4v4fDb2","type":"http://ontosoft.org/software#Software","label":"SWMPr","value":{"http://ontosoft.org/software#hasActiveDevelopment":[{"@type":"TextEntity","id":"http://imcr.ontosoft.org/repository/software/Software-eAtWf4v4fDb2#DevelopmentInformation-A0EKLEAQNKzn","name":"DevelopmentInformation-A0EKLEAQNKzn","type":"http://ontosoft.org/software#DevelopmentInformation","value":"https://github.com/fawda123/SWMPr"}],"http://ontosoft.org/software#hasAdopter":[],"http://ontosoft.org/software#hasAverageRunTime":[],"http://ontosoft.org/software#hasBenchmarkInformation":[],"http://ontosoft.org/software#hasCodeLocation":[{"@type":"Location","id":"http://imcr.ontosoft.org/repository/software/Software-eAtWf4v4fDb2#Location-cffa8TwQue1P","name":"Location-cffa8TwQue1P","type":"http://ontosoft.org/software#Location","value":"https://cran.r-project.org/web/packages/SWMPr/index.html"}],"http://ontosoft.org/software#hasCommitmentOfSupport":[{"@type":"TextEntity","id":"http://imcr.ontosoft.org/repository/software/Software-eAtWf4v4fDb2#TextEntity-iZCemSHJd3lh","name":"TextEntity-iZCemSHJd3lh","type":"http://ontosoft.org/software#TextEntity","value":"http://github.com/fawda123/SWMPr/issues"}],"http://ontosoft.org/software#hasCompositionDescription":[],"http://ontosoft.org/software#hasCreator":[{"@type":"EnumerationEntity","id":"http://imcr.ontosoft.org/repository/software/enumerations#Agent-0Fzdb4ynfmPg","name":"Agent-0Fzdb4ynfmPg","type":"http://www.w3.org/ns/prov#Agent","label":"Marcus W. Beck","value":"Marcus W. Beck"}],"http://ontosoft.org/software#hasDependency":[],"http://ontosoft.org/software#hasDocumentation":[{"@type":"Location","id":"http://imcr.ontosoft.org/repository/software/Software-eAtWf4v4fDb2#Location-mkyNp10cYcoX","name":"Location-mkyNp10cYcoX","type":"http://ontosoft.org/software#Location","value":"https://cran.r-project.org/web/packages/SWMPr/SWMPr.pdf"}],"http://ontosoft.org/software#hasDomainKeywords":[],"http://ontosoft.org/software#hasEmailContact":[],"http://ontosoft.org/software#hasExecutableLocation":[],"http://ontosoft.org/software#hasFundingSources":[],"http://ontosoft.org/software#hasImplementationLanguage":[{"@type":"EnumerationEntity","id":"http://imcr.ontosoft.org/repository/software/enumerations#ProgrammingLanguage-Tkrq9BFxdt0O","name":"ProgrammingLanguage-Tkrq9BFxdt0O","type":"http://ontosoft.org/software#ProgrammingLanguage","label":"R","value":"R"}],"http://ontosoft.org/software#hasInput":[],"http://ontosoft.org/software#hasInputParameter":[],"http://ontosoft.org/software#hasInstallationInstructions":[],"http://ontosoft.org/software#hasInteroperableSoftware":[],"http://ontosoft.org/software#hasLicense":[{"@type":"EnumerationEntity","id":"http://ontosoft.org/software#CreativeCommons","name":"CreativeCommons","type":"http://ontosoft.org/software#License","label":"Creative Commons Zero v1.0 Universal","value":"Creative Commons Zero v1.0 Universal"}],"http://ontosoft.org/software#hasMajorContributor":[],"http://ontosoft.org/software#hasName":[{"@type":"TextEntity","id":"http://imcr.ontosoft.org/repository/software/Software-eAtWf4v4fDb2#TextEntity-OThBUh8Q39KM","name":"TextEntity-OThBUh8Q39KM","type":"http://ontosoft.org/software#TextEntity","value":"SWMPr"}],"http://ontosoft.org/software#hasOtherImplementationDetails":[],"http://ontosoft.org/software#hasOutput":[],"http://ontosoft.org/software#hasPreferredCitation":[],"http://ontosoft.org/software#hasProjectWebsite":[{"@type":"Location","id":"http://imcr.ontosoft.org/repository/software/Software-eAtWf4v4fDb2#Location-2mGK3cx2OoFR","name":"Location-2mGK3cx2OoFR","type":"http://ontosoft.org/software#Location","value":"https://github.com/fawda123/SWMPr"}],"http://ontosoft.org/software#hasPublisher":[{"@type":"EnumerationEntity","id":"http://imcr.ontosoft.org/repository/software/enumerations#Publisher-0k3Oz3jsbwPn","name":"Publisher-0k3Oz3jsbwPn","type":"http://ontosoft.org/software#Publisher","label":"CRAN","value":"CRAN"}],"http://ontosoft.org/software#hasRating":[],"http://ontosoft.org/software#hasRelevantDataSources":[],"http://ontosoft.org/software#hasSalientQualities":[],"http://ontosoft.org/software#hasShortDescription":[{"@type":"TextEntity","id":"http://imcr.ontosoft.org/repository/software/Software-eAtWf4v4fDb2#TextEntity-KRNs1HMjhaaI","name":"TextEntity-KRNs1HMjhaaI","type":"http://ontosoft.org/software#TextEntity","value":"Tools for retrieving, organizing, and analyzing environmental data from the System Wide Monitoring Program of the National Estuarine Research Reserve System <http://cdmo.baruch.sc.edu/>. These tools address common challenges associated with continuous time series data for environmental decision making."}],"http://ontosoft.org/software#hasSoftwareCategory":[{"@type":"EnumerationEntity","id":"http://imcr.ontosoft.org/repository/software/enumerations#SoftwareCategory-gtib5Wlg3FGZ","name":"SoftwareCategory-gtib5Wlg3FGZ","type":"http://ontosoft.org/software#SoftwareCategory","label":"quality control","value":"quality control"},{"@type":"EnumerationEntity","id":"http://imcr.ontosoft.org/repository/software/enumerations#SoftwareCategory-bR7VLgRGWmaC","name":"SoftwareCategory-bR7VLgRGWmaC","type":"http://ontosoft.org/software#SoftwareCategory","label":"assurance","value":"assurance"},{"@type":"EnumerationEntity","id":"http://imcr.ontosoft.org/repository/software/enumerations#SoftwareCategory-8wMj1c2V80io","name":"SoftwareCategory-8wMj1c2V80io","type":"http://ontosoft.org/software#SoftwareCategory","label":"cleaning","value":"cleaning"}],"http://ontosoft.org/software#hasSoftwareCommunity":[{"@type":"TextEntity","id":"http://imcr.ontosoft.org/repository/software/Software-eAtWf4v4fDb2#CommunityInformation-sLNHfpVc17WY","name":"CommunityInformation-sLNHfpVc17WY","type":"http://ontosoft.org/software#CommunityInformation","value":"https://github.com/fawda123/SWMPr"}],"http://ontosoft.org/software#hasSoftwareSupport":[{"@type":"TextEntity","id":"http://imcr.ontosoft.org/repository/software/Software-eAtWf4v4fDb2#TextEntity-p5K0bhr2Qj0z","name":"TextEntity-p5K0bhr2Qj0z","type":"http://ontosoft.org/software#TextEntity","value":"https://github.com/fawda123/SWMPr"}],"http://ontosoft.org/software#hasSoftwareVersion":[],"http://ontosoft.org/software#hasTestData":[],"http://ontosoft.org/software#hasTestInstructions":[],"http://ontosoft.org/software#hasUniqueId":[],"http://ontosoft.org/software#hasUsageInformation":[],"http://ontosoft.org/software#hasUseLimitations":[],"http://ontosoft.org/software#hasUseStatistics":[],"http://ontosoft.org/software#hasUsesAndAssumptions":[],"http://ontosoft.org/software#requiresAverageMemory":[],"http://ontosoft.org/software#similarSoftware":[],"http://ontosoft.org/software#supportsOperatingSystem":[],"http://ontosoft.org/software#usedInPublication":[]},"provenance":{"id":"http://imcr.ontosoft.org/repository/software/Software-eAtWf4v4fDb2/provenance","entities":{"http://imcr.ontosoft.org/repository/software/Software-eAtWf4v4fDb2#TextEntity-KRNs1HMjhaaI":{"id":"http://imcr.ontosoft.org/repository/software/Software-eAtWf4v4fDb2#TextEntity-KRNs1HMjhaaI","revisionOf":{},"generatedBy":"http://imcr.ontosoft.org/repository/software/Software-eAtWf4v4fDb2/provenance#Update-unR5RLHFeSpi","invalidatedBy":{}},"http://imcr.ontosoft.org/repository/software/Software-eAtWf4v4fDb2#TextEntity-iZCemSHJd3lh":{"id":"http://imcr.ontosoft.org/repository/software/Software-eAtWf4v4fDb2#TextEntity-iZCemSHJd3lh","revisionOf":{},"generatedBy":"http://imcr.ontosoft.org/repository/software/Software-eAtWf4v4fDb2/provenance#Update-unR5RLHFeSpi","invalidatedBy":{}},"http://imcr.ontosoft.org/repository/software/Software-eAtWf4v4fDb2#Location-mkyNp10cYcoX":{"id":"http://imcr.ontosoft.org/repository/software/Software-eAtWf4v4fDb2#Location-mkyNp10cYcoX","revisionOf":{},"generatedBy":"http://imcr.ontosoft.org/repository/software/Software-eAtWf4v4fDb2/provenance#Update-unR5RLHFeSpi","invalidatedBy":{}},"http://imcr.ontosoft.org/repository/software/Software-eAtWf4v4fDb2#Location-cffa8TwQue1P":{"id":"http://imcr.ontosoft.org/repository/software/Software-eAtWf4v4fDb2#Location-cffa8TwQue1P","revisionOf":{},"generatedBy":"http://imcr.ontosoft.org/repository/software/Software-eAtWf4v4fDb2/provenance#Update-unR5RLHFeSpi","invalidatedBy":{}},"http://imcr.ontosoft.org/repository/software/Software-eAtWf4v4fDb2#TextEntity-OThBUh8Q39KM":{"id":"http://imcr.ontosoft.org/repository/software/Software-eAtWf4v4fDb2#TextEntity-OThBUh8Q39KM","revisionOf":{},"generatedBy":"http://imcr.ontosoft.org/repository/software/Software-eAtWf4v4fDb2/provenance#Update-unR5RLHFeSpi","invalidatedBy":{}},"http://imcr.ontosoft.org/repository/software/enumerations#Publisher-0k3Oz3jsbwPn":{"id":"http://imcr.ontosoft.org/repository/software/enumerations#Publisher-0k3Oz3jsbwPn","revisionOf":{},"generatedBy":"http://imcr.ontosoft.org/repository/software/Software-eAtWf4v4fDb2/provenance#Update-unR5RLHFeSpi","invalidatedBy":{}},"http://imcr.ontosoft.org/repository/software/enumerations#ProgrammingLanguage-Tkrq9BFxdt0O":{"id":"http://imcr.ontosoft.org/repository/software/enumerations#ProgrammingLanguage-Tkrq9BFxdt0O","revisionOf":{},"generatedBy":"http://imcr.ontosoft.org/repository/software/Software-eAtWf4v4fDb2/provenance#Update-unR5RLHFeSpi","invalidatedBy":{}},"http://imcr.ontosoft.org/repository/software/Software-eAtWf4v4fDb2#CommunityInformation-sLNHfpVc17WY":{"id":"http://imcr.ontosoft.org/repository/software/Software-eAtWf4v4fDb2#CommunityInformation-sLNHfpVc17WY","revisionOf":{},"generatedBy":"http://imcr.ontosoft.org/repository/software/Software-eAtWf4v4fDb2/provenance#Update-unR5RLHFeSpi","invalidatedBy":{}},"http://imcr.ontosoft.org/repository/software/Software-eAtWf4v4fDb2#TextEntity-p5K0bhr2Qj0z":{"id":"http://imcr.ontosoft.org/repository/software/Software-eAtWf4v4fDb2#TextEntity-p5K0bhr2Qj0z","revisionOf":{},"generatedBy":"http://imcr.ontosoft.org/repository/software/Software-eAtWf4v4fDb2/provenance#Update-unR5RLHFeSpi","invalidatedBy":{}},"http://imcr.ontosoft.org/repository/software/enumerations#SoftwareCategory-8wMj1c2V80io":{"id":"http://imcr.ontosoft.org/repository/software/enumerations#SoftwareCategory-8wMj1c2V80io","revisionOf":{},"generatedBy":"http://imcr.ontosoft.org/repository/software/Software-eAtWf4v4fDb2/provenance#Update-unR5RLHFeSpi","invalidatedBy":{}},"http://imcr.ontosoft.org/repository/software/Software-eAtWf4v4fDb2":{"id":"http://imcr.ontosoft.org/repository/software/Software-eAtWf4v4fDb2","revisionOf":{},"generatedBy":"http://imcr.ontosoft.org/repository/software/Software-eAtWf4v4fDb2/provenance#Create-3AYNz39bf6Mi","invalidatedBy":{}},"http://imcr.ontosoft.org/repository/software/enumerations#SoftwareCategory-bR7VLgRGWmaC":{"id":"http://imcr.ontosoft.org/repository/software/enumerations#SoftwareCategory-bR7VLgRGWmaC","revisionOf":{},"generatedBy":"http://imcr.ontosoft.org/repository/software/Software-eAtWf4v4fDb2/provenance#Update-unR5RLHFeSpi","invalidatedBy":{}},"http://ontosoft.org/software#CreativeCommons":{"id":"http://ontosoft.org/software#CreativeCommons","revisionOf":{},"generatedBy":"http://imcr.ontosoft.org/repository/software/Software-eAtWf4v4fDb2/provenance#Update-unR5RLHFeSpi","invalidatedBy":{}},"http://imcr.ontosoft.org/repository/software/Software-eAtWf4v4fDb2#Location-2mGK3cx2OoFR":{"id":"http://imcr.ontosoft.org/repository/software/Software-eAtWf4v4fDb2#Location-2mGK3cx2OoFR","revisionOf":{},"generatedBy":"http://imcr.ontosoft.org/repository/software/Software-eAtWf4v4fDb2/provenance#Update-unR5RLHFeSpi","invalidatedBy":{}},"http://imcr.ontosoft.org/repository/software/Software-eAtWf4v4fDb2#DevelopmentInformation-A0EKLEAQNKzn":{"id":"http://imcr.ontosoft.org/repository/software/Software-eAtWf4v4fDb2#DevelopmentInformation-A0EKLEAQNKzn","revisionOf":{},"generatedBy":"http://imcr.ontosoft.org/repository/software/Software-eAtWf4v4fDb2/provenance#Update-unR5RLHFeSpi","invalidatedBy":{}},"http://imcr.ontosoft.org/repository/software/Software-eAtWf4v4fDb2#Agent-WgcYaEav9LX2":{"id":"http://imcr.ontosoft.org/repository/software/Software-eAtWf4v4fDb2#Agent-WgcYaEav9LX2","revisionOf":{},"generatedBy":"http://imcr.ontosoft.org/repository/software/Software-eAtWf4v4fDb2/provenance#Update-unR5RLHFeSpi","invalidatedBy":{}},"http://imcr.ontosoft.org/repository/software/enumerations#SoftwareCategory-gtib5Wlg3FGZ":{"id":"http://imcr.ontosoft.org/repository/software/enumerations#SoftwareCategory-gtib5Wlg3FGZ","revisionOf":{},"generatedBy":"http://imcr.ontosoft.org/repository/software/Software-eAtWf4v4fDb2/provenance#Update-unR5RLHFeSpi","invalidatedBy":{}}},"activities":{"http://imcr.ontosoft.org/repository/software/Software-eAtWf4v4fDb2/provenance#Update-unR5RLHFeSpi":{"id":"http://imcr.ontosoft.org/repository/software/Software-eAtWf4v4fDb2/provenance#Update-unR5RLHFeSpi","time":1553136268112,"agentId":"http://imcr.ontosoft.org/repository/users/csmith"},"http://imcr.ontosoft.org/repository/software/Software-eAtWf4v4fDb2/provenance#Create-3AYNz39bf6Mi":{"id":"http://imcr.ontosoft.org/repository/software/Software-eAtWf4v4fDb2/provenance#Create-3AYNz39bf6Mi","time":1553136031715,"agentId":"http://imcr.ontosoft.org/repository/users/csmith"}},"agents":{"http://imcr.ontosoft.org/repository/users/csmith":{"id":"http://imcr.ontosoft.org/repository/users/csmith","name":"csmith"}}},"permission":{"id":"http://imcr.ontosoft.org/repository/software/Software-eAtWf4v4fDb2/permission","owners":[{"id":"http://imcr.ontosoft.org/repository/users/csmith"}],"type":{},"authorizations":{"http://imcr.ontosoft.org/repository/software/Software-eAtWf4v4fDb2/permission#Auth-b5uDQp3wlOjZ":{"id":"http://imcr.ontosoft.org/repository/software/Software-eAtWf4v4fDb2/permission#Auth-b5uDQp3wlOjZ","agentId":"http://imcr.ontosoft.org/repository/users/csmith","agentName":"csmith","accessMode":{"id":"http://www.w3.org/ns/auth/acl#Write","mode":"Write"},"accessToObjId":"http://imcr.ontosoft.org/repository/software/Software-eAtWf4v4fDb2"}}}}
