{"@type":"Software","id":"http://imcr.ontosoft.org/repository/software/Software-pM5hgguOs0ca","name":"Software-pM5hgguOs0ca","type":"http://ontosoft.org/software#Software","label":"exifr","value":{"http://ontosoft.org/software#hasActiveDevelopment":[{"@type":"TextEntity","id":"http://imcr.ontosoft.org/repository/software/Software-pM5hgguOs0ca#DevelopmentInformation-7J6p4ZzJqXbl","name":"DevelopmentInformation-7J6p4ZzJqXbl","type":"http://ontosoft.org/software#DevelopmentInformation","value":"https://github.com/paleolimbot/exifr"}],"http://ontosoft.org/software#hasAdopter":[],"http://ontosoft.org/software#hasAverageRunTime":[],"http://ontosoft.org/software#hasBenchmarkInformation":[],"http://ontosoft.org/software#hasCodeLocation":[{"@type":"Location","id":"http://imcr.ontosoft.org/repository/software/Software-pM5hgguOs0ca#Location-eh6rphG0w80h","name":"Location-eh6rphG0w80h","type":"http://ontosoft.org/software#Location","value":"https://cran.r-project.org/web/packages/exifr/index.html"}],"http://ontosoft.org/software#hasCommitmentOfSupport":[{"@type":"TextEntity","id":"http://imcr.ontosoft.org/repository/software/Software-pM5hgguOs0ca#TextEntity-gu3HYhaV0wx5","name":"TextEntity-gu3HYhaV0wx5","type":"http://ontosoft.org/software#TextEntity","value":"https://github.com/paleolimbot/exifr/issues"}],"http://ontosoft.org/software#hasCompositionDescription":[],"http://ontosoft.org/software#hasCreator":[{"@type":"EnumerationEntity","id":"http://imcr.ontosoft.org/repository/software/enumerations#Agent-m4BOIsDG9uXO","name":"Agent-m4BOIsDG9uXO","type":"http://www.w3.org/ns/prov#Agent","label":"Dewey Dunnington","value":"Dewey Dunnington"},{"@type":"EnumerationEntity","id":"http://imcr.ontosoft.org/repository/software/enumerations#Agent-DnjhbuXGxKpD","name":"Agent-DnjhbuXGxKpD","type":"http://www.w3.org/ns/prov#Agent","label":"Phil Harvey","value":"Phil Harvey"}],"http://ontosoft.org/software#hasDependency":[],"http://ontosoft.org/software#hasDocumentation":[{"@type":"Location","id":"http://imcr.ontosoft.org/repository/software/Software-pM5hgguOs0ca#Location-u5WLWzV5zHM6","name":"Location-u5WLWzV5zHM6","type":"http://ontosoft.org/software#Location","value":"https://cran.r-project.org/web/packages/exifr/exifr.pdf"}],"http://ontosoft.org/software#hasDomainKeywords":[],"http://ontosoft.org/software#hasEmailContact":[],"http://ontosoft.org/software#hasExecutableLocation":[],"http://ontosoft.org/software#hasFundingSources":[],"http://ontosoft.org/software#hasImplementationLanguage":[{"@type":"EnumerationEntity","id":"http://imcr.ontosoft.org/repository/software/enumerations#ProgrammingLanguage-Tkrq9BFxdt0O","name":"ProgrammingLanguage-Tkrq9BFxdt0O","type":"http://ontosoft.org/software#ProgrammingLanguage","label":"R","value":"R"}],"http://ontosoft.org/software#hasInput":[],"http://ontosoft.org/software#hasInputParameter":[],"http://ontosoft.org/software#hasInstallationInstructions":[],"http://ontosoft.org/software#hasInteroperableSoftware":[],"http://ontosoft.org/software#hasLicense":[{"@type":"EnumerationEntity","id":"http://imcr.ontosoft.org/repository/software/enumerations#License-qCP5R777MVwz","name":"License-qCP5R777MVwz","type":"http://ontosoft.org/software#License","label":"GPLv2 license","value":"GPLv2 license"}],"http://ontosoft.org/software#hasMajorContributor":[],"http://ontosoft.org/software#hasName":[{"@type":"TextEntity","id":"http://imcr.ontosoft.org/repository/software/Software-pM5hgguOs0ca#TextEntity-9B9Vkox3PhPw","name":"TextEntity-9B9Vkox3PhPw","type":"http://ontosoft.org/software#TextEntity","value":"exifr"}],"http://ontosoft.org/software#hasOtherImplementationDetails":[],"http://ontosoft.org/software#hasOutput":[],"http://ontosoft.org/software#hasPreferredCitation":[],"http://ontosoft.org/software#hasProjectWebsite":[{"@type":"Location","id":"http://imcr.ontosoft.org/repository/software/Software-pM5hgguOs0ca#Location-7v7RBGgmFV2E","name":"Location-7v7RBGgmFV2E","type":"http://ontosoft.org/software#Location","value":"https://github.com/paleolimbot/exifr"}],"http://ontosoft.org/software#hasPublisher":[{"@type":"EnumerationEntity","id":"http://imcr.ontosoft.org/repository/software/enumerations#Publisher-0k3Oz3jsbwPn","name":"Publisher-0k3Oz3jsbwPn","type":"http://ontosoft.org/software#Publisher","label":"CRAN","value":"CRAN"}],"http://ontosoft.org/software#hasRating":[],"http://ontosoft.org/software#hasRelevantDataSources":[],"http://ontosoft.org/software#hasSalientQualities":[],"http://ontosoft.org/software#hasShortDescription":[{"@type":"TextEntity","id":"http://imcr.ontosoft.org/repository/software/Software-pM5hgguOs0ca#TextEntity-yAr79DG0ZRwY","name":"TextEntity-yAr79DG0ZRwY","type":"http://ontosoft.org/software#TextEntity","value":"Reads EXIF data using ExifTool <http://www.sno.phy.queensu.ca/~phil/exiftool/> and returns results as a data frame. ExifTool is a platform-independent Perl library plus a command-line application for reading, writing and editing meta information in a wide variety of files. ExifTool supports many different metadata formats including EXIF, GPS, IPTC, XMP, JFIF, GeoTIFF, ICC Profile, Photoshop IRB, FlashPix, AFCP and ID3, as well as the maker notes of many digital cameras by Canon, Casio, FLIR, FujiFilm, GE, HP, JVC/Victor, Kodak, Leaf, Minolta/Konica-Minolta, Motorola, Nikon, Nintendo, Olympus/Epson, Panasonic/Leica, Pentax/Asahi, Phase One, Reconyx, Ricoh, Samsung, Sanyo, Sigma/Foveon and Sony."}],"http://ontosoft.org/software#hasSoftwareCategory":[{"@type":"EnumerationEntity","id":"http://imcr.ontosoft.org/repository/software/enumerations#SoftwareCategory-02I2h7spnEo2","name":"SoftwareCategory-02I2h7spnEo2","type":"http://ontosoft.org/software#SoftwareCategory","label":"describing","value":"describing"},{"@type":"EnumerationEntity","id":"http://imcr.ontosoft.org/repository/software/enumerations#SoftwareCategory-BZp0woZlEi2f","name":"SoftwareCategory-BZp0woZlEi2f","type":"http://ontosoft.org/software#SoftwareCategory","label":"reporting","value":"reporting"},{"@type":"EnumerationEntity","id":"http://imcr.ontosoft.org/repository/software/enumerations#SoftwareCategory-qq8xWna0fDwR","name":"SoftwareCategory-qq8xWna0fDwR","type":"http://ontosoft.org/software#SoftwareCategory","label":"collection","value":"collection"},{"@type":"EnumerationEntity","id":"http://imcr.ontosoft.org/repository/software/enumerations#SoftwareCategory-DKqMYJ7CDFYa","name":"SoftwareCategory-DKqMYJ7CDFYa","type":"http://ontosoft.org/software#SoftwareCategory","label":"import","value":"import"}],"http://ontosoft.org/software#hasSoftwareCommunity":[{"@type":"TextEntity","id":"http://imcr.ontosoft.org/repository/software/Software-pM5hgguOs0ca#CommunityInformation-V0ymtL4XOW8G","name":"CommunityInformation-V0ymtL4XOW8G","type":"http://ontosoft.org/software#CommunityInformation","value":"https://github.com/paleolimbot/exifr"}],"http://ontosoft.org/software#hasSoftwareSupport":[{"@type":"TextEntity","id":"http://imcr.ontosoft.org/repository/software/Software-pM5hgguOs0ca#TextEntity-Kru4j8tJmkmI","name":"TextEntity-Kru4j8tJmkmI","type":"http://ontosoft.org/software#TextEntity","value":"https://cran.r-project.org/web/packages/exifr/index.html"}],"http://ontosoft.org/software#hasSoftwareVersion":[],"http://ontosoft.org/software#hasTestData":[],"http://ontosoft.org/software#hasTestInstructions":[],"http://ontosoft.org/software#hasUniqueId":[],"http://ontosoft.org/software#hasUsageInformation":[],"http://ontosoft.org/software#hasUseLimitations":[],"http://ontosoft.org/software#hasUseStatistics":[],"http://ontosoft.org/software#hasUsesAndAssumptions":[],"http://ontosoft.org/software#requiresAverageMemory":[],"http://ontosoft.org/software#similarSoftware":[],"http://ontosoft.org/software#supportsOperatingSystem":[],"http://ontosoft.org/software#usedInPublication":[]},"provenance":{"id":"http://imcr.ontosoft.org/repository/software/Software-pM5hgguOs0ca/provenance","entities":{"http://imcr.ontosoft.org/repository/software/enumerations#SoftwareCategory-02I2h7spnEo2":{"id":"http://imcr.ontosoft.org/repository/software/enumerations#SoftwareCategory-02I2h7spnEo2","revisionOf":{},"generatedBy":"http://imcr.ontosoft.org/repository/software/Software-pM5hgguOs0ca/provenance#Update-ZoeDFBDYCtyC","invalidatedBy":{}},"http://imcr.ontosoft.org/repository/software/enumerations#License-qCP5R777MVwz":{"id":"http://imcr.ontosoft.org/repository/software/enumerations#License-qCP5R777MVwz","revisionOf":{},"generatedBy":"http://imcr.ontosoft.org/repository/software/Software-pM5hgguOs0ca/provenance#Update-ZoeDFBDYCtyC","invalidatedBy":{}},"http://imcr.ontosoft.org/repository/software/Software-pM5hgguOs0ca#TextEntity-9B9Vkox3PhPw":{"id":"http://imcr.ontosoft.org/repository/software/Software-pM5hgguOs0ca#TextEntity-9B9Vkox3PhPw","revisionOf":{},"generatedBy":"http://imcr.ontosoft.org/repository/software/Software-pM5hgguOs0ca/provenance#Update-ZoeDFBDYCtyC","invalidatedBy":{}},"http://imcr.ontosoft.org/repository/software/enumerations#SoftwareCategory-bxzazkjAfJVK":{"id":"http://imcr.ontosoft.org/repository/software/enumerations#SoftwareCategory-bxzazkjAfJVK","revisionOf":{},"generatedBy":"http://imcr.ontosoft.org/repository/software/Software-pM5hgguOs0ca/provenance#Update-ZoeDFBDYCtyC","invalidatedBy":"http://imcr.ontosoft.org/repository/software/Software-pM5hgguOs0ca/provenance#Update-vVHTN5vWx07r"},"http://imcr.ontosoft.org/repository/software/enumerations#Publisher-0k3Oz3jsbwPn":{"id":"http://imcr.ontosoft.org/repository/software/enumerations#Publisher-0k3Oz3jsbwPn","revisionOf":{},"generatedBy":"http://imcr.ontosoft.org/repository/software/Software-pM5hgguOs0ca/provenance#Update-ZoeDFBDYCtyC","invalidatedBy":{}},"http://imcr.ontosoft.org/repository/software/Software-pM5hgguOs0ca#TextEntity-Kru4j8tJmkmI":{"id":"http://imcr.ontosoft.org/repository/software/Software-pM5hgguOs0ca#TextEntity-Kru4j8tJmkmI","revisionOf":{},"generatedBy":"http://imcr.ontosoft.org/repository/software/Software-pM5hgguOs0ca/provenance#Update-ZoeDFBDYCtyC","invalidatedBy":{}},"http://imcr.ontosoft.org/repository/software/Software-pM5hgguOs0ca#TextEntity-yAr79DG0ZRwY":{"id":"http://imcr.ontosoft.org/repository/software/Software-pM5hgguOs0ca#TextEntity-yAr79DG0ZRwY","revisionOf":{},"generatedBy":"http://imcr.ontosoft.org/repository/software/Software-pM5hgguOs0ca/provenance#Update-ZoeDFBDYCtyC","invalidatedBy":{}},"http://imcr.ontosoft.org/repository/software/enumerations#ProgrammingLanguage-Tkrq9BFxdt0O":{"id":"http://imcr.ontosoft.org/repository/software/enumerations#ProgrammingLanguage-Tkrq9BFxdt0O","revisionOf":{},"generatedBy":"http://imcr.ontosoft.org/repository/software/Software-pM5hgguOs0ca/provenance#Update-ZoeDFBDYCtyC","invalidatedBy":{}},"http://imcr.ontosoft.org/repository/software/enumerations#SoftwareCategory-6gehlnfmapph":{"id":"http://imcr.ontosoft.org/repository/software/enumerations#SoftwareCategory-6gehlnfmapph","revisionOf":{},"generatedBy":"http://imcr.ontosoft.org/repository/software/Software-pM5hgguOs0ca/provenance#Update-ZoeDFBDYCtyC","invalidatedBy":"http://imcr.ontosoft.org/repository/software/Software-pM5hgguOs0ca/provenance#Update-bjKdEXCLEh2Z"},"http://imcr.ontosoft.org/repository/software/enumerations#SoftwareCategory-qq8xWna0fDwR":{"id":"http://imcr.ontosoft.org/repository/software/enumerations#SoftwareCategory-qq8xWna0fDwR","revisionOf":{},"generatedBy":"http://imcr.ontosoft.org/repository/software/Software-pM5hgguOs0ca/provenance#Update-ZoeDFBDYCtyC","invalidatedBy":{}},"http://imcr.ontosoft.org/repository/software/Software-pM5hgguOs0ca#Location-eh6rphG0w80h":{"id":"http://imcr.ontosoft.org/repository/software/Software-pM5hgguOs0ca#Location-eh6rphG0w80h","revisionOf":{},"generatedBy":"http://imcr.ontosoft.org/repository/software/Software-pM5hgguOs0ca/provenance#Update-ZoeDFBDYCtyC","invalidatedBy":{}},"http://imcr.ontosoft.org/repository/software/Software-pM5hgguOs0ca#Location-7v7RBGgmFV2E":{"id":"http://imcr.ontosoft.org/repository/software/Software-pM5hgguOs0ca#Location-7v7RBGgmFV2E","revisionOf":{},"generatedBy":"http://imcr.ontosoft.org/repository/software/Software-pM5hgguOs0ca/provenance#Update-ZoeDFBDYCtyC","invalidatedBy":{}},"http://imcr.ontosoft.org/repository/software/enumerations#SoftwareCategory-BZp0woZlEi2f":{"id":"http://imcr.ontosoft.org/repository/software/enumerations#SoftwareCategory-BZp0woZlEi2f","revisionOf":{},"generatedBy":"http://imcr.ontosoft.org/repository/software/Software-pM5hgguOs0ca/provenance#Update-vVHTN5vWx07r","invalidatedBy":{}},"http://imcr.ontosoft.org/repository/software/Software-pM5hgguOs0ca#TextEntity-gu3HYhaV0wx5":{"id":"http://imcr.ontosoft.org/repository/software/Software-pM5hgguOs0ca#TextEntity-gu3HYhaV0wx5","revisionOf":{},"generatedBy":"http://imcr.ontosoft.org/repository/software/Software-pM5hgguOs0ca/provenance#Update-ZoeDFBDYCtyC","invalidatedBy":{}},"http://imcr.ontosoft.org/repository/software/Software-pM5hgguOs0ca#Location-u5WLWzV5zHM6":{"id":"http://imcr.ontosoft.org/repository/software/Software-pM5hgguOs0ca#Location-u5WLWzV5zHM6","revisionOf":{},"generatedBy":"http://imcr.ontosoft.org/repository/software/Software-pM5hgguOs0ca/provenance#Update-ZoeDFBDYCtyC","invalidatedBy":{}},"http://imcr.ontosoft.org/repository/software/Software-pM5hgguOs0ca":{"id":"http://imcr.ontosoft.org/repository/software/Software-pM5hgguOs0ca","revisionOf":{},"generatedBy":"http://imcr.ontosoft.org/repository/software/Software-pM5hgguOs0ca/provenance#Create-5yyPiU0WXitR","invalidatedBy":{}},"http://imcr.ontosoft.org/repository/software/enumerations#SoftwareCategory-DKqMYJ7CDFYa":{"id":"http://imcr.ontosoft.org/repository/software/enumerations#SoftwareCategory-DKqMYJ7CDFYa","revisionOf":{},"generatedBy":"http://imcr.ontosoft.org/repository/software/Software-pM5hgguOs0ca/provenance#Update-bjKdEXCLEh2Z","invalidatedBy":{}},"http://imcr.ontosoft.org/repository/software/Software-pM5hgguOs0ca#Agent-c994jazoyiW2":{"id":"http://imcr.ontosoft.org/repository/software/Software-pM5hgguOs0ca#Agent-c994jazoyiW2","revisionOf":{},"generatedBy":"http://imcr.ontosoft.org/repository/software/Software-pM5hgguOs0ca/provenance#Update-ZoeDFBDYCtyC","invalidatedBy":{}},"http://imcr.ontosoft.org/repository/software/Software-pM5hgguOs0ca#Agent-92PcHN3oNCQM":{"id":"http://imcr.ontosoft.org/repository/software/Software-pM5hgguOs0ca#Agent-92PcHN3oNCQM","revisionOf":{},"generatedBy":"http://imcr.ontosoft.org/repository/software/Software-pM5hgguOs0ca/provenance#Update-ZoeDFBDYCtyC","invalidatedBy":{}},"http://imcr.ontosoft.org/repository/software/Software-pM5hgguOs0ca#DevelopmentInformation-7J6p4ZzJqXbl":{"id":"http://imcr.ontosoft.org/repository/software/Software-pM5hgguOs0ca#DevelopmentInformation-7J6p4ZzJqXbl","revisionOf":{},"generatedBy":"http://imcr.ontosoft.org/repository/software/Software-pM5hgguOs0ca/provenance#Update-ZoeDFBDYCtyC","invalidatedBy":{}},"http://imcr.ontosoft.org/repository/software/Software-pM5hgguOs0ca#CommunityInformation-V0ymtL4XOW8G":{"id":"http://imcr.ontosoft.org/repository/software/Software-pM5hgguOs0ca#CommunityInformation-V0ymtL4XOW8G","revisionOf":{},"generatedBy":"http://imcr.ontosoft.org/repository/software/Software-pM5hgguOs0ca/provenance#Update-ZoeDFBDYCtyC","invalidatedBy":{}}},"activities":{"http://imcr.ontosoft.org/repository/software/Software-pM5hgguOs0ca/provenance#Create-5yyPiU0WXitR":{"id":"http://imcr.ontosoft.org/repository/software/Software-pM5hgguOs0ca/provenance#Create-5yyPiU0WXitR","time":1553978671490,"agentId":"http://imcr.ontosoft.org/repository/users/csmith"},"http://imcr.ontosoft.org/repository/software/Software-pM5hgguOs0ca/provenance#Update-ZoeDFBDYCtyC":{"id":"http://imcr.ontosoft.org/repository/software/Software-pM5hgguOs0ca/provenance#Update-ZoeDFBDYCtyC","time":1553978912189,"agentId":"http://imcr.ontosoft.org/repository/users/csmith"},"http://imcr.ontosoft.org/repository/software/Software-pM5hgguOs0ca/provenance#Update-bjKdEXCLEh2Z":{"id":"http://imcr.ontosoft.org/repository/software/Software-pM5hgguOs0ca/provenance#Update-bjKdEXCLEh2Z","time":1562896778813,"agentId":"http://imcr.ontosoft.org/repository/users/csmith"},"http://imcr.ontosoft.org/repository/software/Software-pM5hgguOs0ca/provenance#Update-vVHTN5vWx07r":{"id":"http://imcr.ontosoft.org/repository/software/Software-pM5hgguOs0ca/provenance#Update-vVHTN5vWx07r","time":1562897799376,"agentId":"http://imcr.ontosoft.org/repository/users/csmith"}},"agents":{"http://imcr.ontosoft.org/repository/users/csmith":{"id":"http://imcr.ontosoft.org/repository/users/csmith","name":"csmith"}}},"permission":{"id":"http://imcr.ontosoft.org/repository/software/Software-pM5hgguOs0ca/permission","owners":[{"id":"http://imcr.ontosoft.org/repository/users/csmith"}],"type":{},"authorizations":{"http://imcr.ontosoft.org/repository/software/Software-pM5hgguOs0ca/permission#Auth-IDO8CxZsUMkJ":{"id":"http://imcr.ontosoft.org/repository/software/Software-pM5hgguOs0ca/permission#Auth-IDO8CxZsUMkJ","agentId":"http://imcr.ontosoft.org/repository/users/csmith","agentName":"csmith","accessMode":{"id":"http://www.w3.org/ns/auth/acl#Write","mode":"Write"},"accessToObjId":"http://imcr.ontosoft.org/repository/software/Software-pM5hgguOs0ca"}}}}
